{"cameraMode":{"drawMode":0,"name":"Shaded","section":"Shading Mode"},"sceneLighting":true,"audioPlay":false,"sceneViewState":{"showFog":true,"showMaterialUpdate":false,"showSkybox":true,"showFlares":true,"showImageEffects":true,"showParticleSystems":true},"in2DMode":false,"pivot":{"x":233.55999755859376,"y":6.973215579986572,"z":87.54000854492188},"rotation":{"x":-0.09460125118494034,"y":-0.5704283118247986,"z":0.06635935604572296,"w":-0.8131780624389648},"size":378.59368896484377,"orthographic":false}